{
  "structure": [
    {
      "Field": "id",
      "Type": "int(11)",
      "Null": "NO",
      "Key": "PRI",
      "Default": null,
      "Extra": "auto_increment"
    },
    {
      "Field": "user_id",
      "Type": "int(11)",
      "Null": "NO",
      "Key": "MUL",
      "Default": null,
      "Extra": ""
    },
    {
      "Field": "nama_lengkap",
      "Type": "varchar(255)",
      "Null": "NO",
      "Key": "",
      "Default": null,
      "Extra": ""
    },
    {
      "Field": "nim",
      "Type": "varchar(50)",
      "Null": "YES",
      "Key": "",
      "Default": null,
      "Extra": ""
    },
    {
      "Field": "instansi",
      "Type": "varchar(255)",
      "Null": "YES",
      "Key": "",
      "Default": null,
      "Extra": ""
    },
    {
      "Field": "bidang",
      "Type": "varchar(100)",
      "Null": "YES",
      "Key": "",
      "Default": null,
      "Extra": ""
    },
    {
      "Field": "jurusan",
      "Type": "varchar(255)",
      "Null": "YES",
      "Key": "",
      "Default": null,
      "Extra": ""
    },
    {
      "Field": "divisi_penempatan",
      "Type": "varchar(255)",
      "Null": "YES",
      "Key": "",
      "Default": null,
      "Extra": ""
    },
    {
      "Field": "waktu_mulai",
      "Type": "date",
      "Null": "YES",
      "Key": "",
      "Default": null,
      "Extra": ""
    },
    {
      "Field": "waktu_selesai",
      "Type": "date",
      "Null": "YES",
      "Key": "",
      "Default": null,
      "Extra": ""
    },
    {
      "Field": "surat_pengantar",
      "Type": "varchar(500)",
      "Null": "YES",
      "Key": "",
      "Default": null,
      "Extra": ""
    },
    {
      "Field": "status",
      "Type": "enum('formulir','verifikasi','diterima','ditolak','selesai')",
      "Null": "YES",
      "Key": "",
      "Default": "formulir",
      "Extra": ""
    },
    {
      "Field": "catatan",
      "Type": "text",
      "Null": "YES",
      "Key": "",
      "Default": null,
      "Extra": ""
    },
    {
      "Field": "created_at",
      "Type": "timestamp",
      "Null": "NO",
      "Key": "",
      "Default": "current_timestamp()",
      "Extra": ""
    },
    {
      "Field": "updated_at",
      "Type": "timestamp",
      "Null": "NO",
      "Key": "",
      "Default": "current_timestamp()",
      "Extra": "on update current_timestamp()"
    }
  ],
  "statusColumn": {
    "Field": "status",
    "Type": "enum('formulir','verifikasi','diterima','ditolak','selesai')",
    "Null": "YES",
    "Key": "",
    "Default": "formulir",
    "Extra": ""
  }
}